torch/extensions/__init__.py
torch/extensions/extension.pyd
torch_extensions-0.1.9.dist-info/METADATA
torch_extensions-0.1.9.dist-info/WHEEL
torch_extensions-0.1.9.dist-info/top_level.txt
torch_extensions-0.1.9.dist-info/RECORD
