Metadata-Version: 2.4
Name: torch-extensions
Version: 0.1.9
Summary: pytorch通用模型导出
Author: zhumingwu
Author-email: zhumingwu@126.com
Requires-Dist: torch>=2.2.0
Requires-Dist: cython>=0.29.0
Requires-Dist: setuptools>=61.0.0
Requires-Dist: numpy>=1.20
Dynamic: author
Dynamic: author-email
Dynamic: requires-dist
Dynamic: summary
